{"box_data": [{"position": {"minX": 475.75, "minY": 254.625, "maxX": 492.75, "maxY": 270.75}, "class_id": 3, "box_caption": "open_circuit 0.514", "scores": {"class_score": 0.513671875}, "domain": "pixel"}, {"position": {"minX": 521.0, "minY": 360.25, "maxX": 541.0, "maxY": 379.75}, "class_id": 3, "box_caption": "open_circuit 0.403", "scores": {"class_score": 0.40283203125}, "domain": "pixel"}, {"position": {"minX": 318.5, "minY": 309.75, "maxX": 333.5, "maxY": 336.25}, "class_id": 3, "box_caption": "open_circuit 0.245", "scores": {"class_score": 0.2451171875}, "domain": "pixel"}, {"position": {"minX": 316.25, "minY": 323.75, "maxX": 338.75, "maxY": 396.75}, "class_id": 6, "box_caption": "spurious_copper 0.020", "scores": {"class_score": 0.0198516845703125}, "domain": "pixel"}, {"position": {"minX": 318.5, "minY": 309.75, "maxX": 333.5, "maxY": 336.25}, "class_id": 2, "box_caption": "mouse_bite 0.011", "scores": {"class_score": 0.01141357421875}, "domain": "pixel"}, {"position": {"minX": 475.0, "minY": 247.5, "maxX": 494.5, "maxY": 277.5}, "class_id": 3, "box_caption": "open_circuit 0.010", "scores": {"class_score": 0.00972747802734375}, "domain": "pixel"}, {"position": {"minX": 515.0, "minY": 566.0, "maxX": 557.0, "maxY": 599.0}, "class_id": 5, "box_caption": "spur 0.008", "scores": {"class_score": 0.007843017578125}, "domain": "pixel"}, {"position": {"minX": 599.0, "minY": 565.5, "maxX": 622.0, "maxY": 596.5}, "class_id": 5, "box_caption": "spur 0.006", "scores": {"class_score": 0.006298065185546875}, "domain": "pixel"}, {"position": {"minX": 475.5, "minY": 253.5, "maxX": 494.0, "maxY": 271.5}, "class_id": 2, "box_caption": "mouse_bite 0.006", "scores": {"class_score": 0.006183624267578125}, "domain": "pixel"}, {"position": {"minX": 522.5, "minY": 354.75, "maxX": 543.5, "maxY": 385.25}, "class_id": 3, "box_caption": "open_circuit 0.006", "scores": {"class_score": 0.005741119384765625}, "domain": "pixel"}, {"position": {"minX": 560.5, "minY": 16.4375, "maxX": 580.5, "maxY": 40.6875}, "class_id": 5, "box_caption": "spur 0.003", "scores": {"class_score": 0.003299713134765625}, "domain": "pixel"}, {"position": {"minX": 422.5, "minY": 10.9921875, "maxX": 449.0, "maxY": 29.625}, "class_id": 5, "box_caption": "spur 0.003", "scores": {"class_score": 0.00324249267578125}, "domain": "pixel"}, {"position": {"minX": 335.25, "minY": 22.28125, "maxX": 380.75, "maxY": 72.0}, "class_id": 5, "box_caption": "spur 0.003", "scores": {"class_score": 0.0026702880859375}, "domain": "pixel"}, {"position": {"minX": 475.5, "minY": 253.5, "maxX": 494.0, "maxY": 271.5}, "class_id": 6, "box_caption": "spurious_copper 0.002", "scores": {"class_score": 0.00246429443359375}, "domain": "pixel"}, {"position": {"minX": 474.75, "minY": 249.875, "maxX": 507.25, "maxY": 273.75}, "class_id": 6, "box_caption": "spurious_copper 0.002", "scores": {"class_score": 0.00243377685546875}, "domain": "pixel"}, {"position": {"minX": 474.75, "minY": 249.875, "maxX": 507.25, "maxY": 273.75}, "class_id": 3, "box_caption": "open_circuit 0.002", "scores": {"class_score": 0.002105712890625}, "domain": "pixel"}, {"position": {"minX": 475.5, "minY": 253.5, "maxX": 494.0, "maxY": 271.5}, "class_id": 5, "box_caption": "spur 0.002", "scores": {"class_score": 0.0020847320556640625}, "domain": "pixel"}, {"position": {"minX": 331.5, "minY": 15.921875, "maxX": 369.0, "maxY": 66.4375}, "class_id": 5, "box_caption": "spur 0.002", "scores": {"class_score": 0.00200653076171875}, "domain": "pixel"}, {"position": {"minX": 475.5, "minY": 253.5, "maxX": 494.0, "maxY": 271.5}, "class_id": 1, "box_caption": "missing_hole 0.002", "scores": {"class_score": 0.00189208984375}, "domain": "pixel"}, {"position": {"minX": 410.75, "minY": 2.875, "maxX": 442.25, "maxY": 25.0625}, "class_id": 4, "box_caption": "short 0.002", "scores": {"class_score": 0.0018177032470703125}, "domain": "pixel"}, {"position": {"minX": 411.75, "minY": 12.4140625, "maxX": 438.75, "maxY": 33.8125}, "class_id": 4, "box_caption": "short 0.002", "scores": {"class_score": 0.0017442703247070312}, "domain": "pixel"}, {"position": {"minX": 484.0, "minY": 437.75, "maxX": 522.0, "maxY": 472.75}, "class_id": 5, "box_caption": "spur 0.002", "scores": {"class_score": 0.0017213821411132812}, "domain": "pixel"}, {"position": {"minX": 598.0, "minY": 563.0, "maxX": 635.0, "maxY": 601.0}, "class_id": 5, "box_caption": "spur 0.002", "scores": {"class_score": 0.0016546249389648438}, "domain": "pixel"}, {"position": {"minX": 557.5, "minY": 12.875, "maxX": 582.5, "maxY": 65.0625}, "class_id": 5, "box_caption": "spur 0.002", "scores": {"class_score": 0.001598358154296875}, "domain": "pixel"}, {"position": {"minX": 475.5, "minY": 253.5, "maxX": 494.0, "maxY": 271.5}, "class_id": 4, "box_caption": "short 0.002", "scores": {"class_score": 0.0015096664428710938}, "domain": "pixel"}, {"position": {"minX": 521.0, "minY": 360.25, "maxX": 541.0, "maxY": 379.75}, "class_id": 2, "box_caption": "mouse_bite 0.002", "scores": {"class_score": 0.0015039443969726562}, "domain": "pixel"}, {"position": {"minX": 517.5, "minY": 358.0, "maxX": 538.5, "maxY": 377.0}, "class_id": 3, "box_caption": "open_circuit 0.001", "scores": {"class_score": 0.0013828277587890625}, "domain": "pixel"}, {"position": {"minX": 183.625, "minY": 423.0, "maxX": 197.875, "maxY": 437.0}, "class_id": 1, "box_caption": "missing_hole 0.001", "scores": {"class_score": 0.001323699951171875}, "domain": "pixel"}, {"position": {"minX": 319.25, "minY": 310.0, "maxX": 334.25, "maxY": 335.5}, "class_id": 6, "box_caption": "spurious_copper 0.001", "scores": {"class_score": 0.0013074874877929688}, "domain": "pixel"}, {"position": {"minX": 518.0, "minY": 360.75, "maxX": 547.0, "maxY": 384.25}, "class_id": 3, "box_caption": "open_circuit 0.001", "scores": {"class_score": 0.0012989044189453125}, "domain": "pixel"}, {"position": {"minX": 521.0, "minY": 360.25, "maxX": 541.0, "maxY": 379.75}, "class_id": 5, "box_caption": "spur 0.001", "scores": {"class_score": 0.001293182373046875}, "domain": "pixel"}, {"position": {"minX": 318.5, "minY": 309.75, "maxX": 333.5, "maxY": 336.25}, "class_id": 4, "box_caption": "short 0.001", "scores": {"class_score": 0.0011854171752929688}, "domain": "pixel"}, {"position": {"minX": 480.0, "minY": 246.25, "maxX": 551.0, "maxY": 275.75}, "class_id": 6, "box_caption": "spurious_copper 0.001", "scores": {"class_score": 0.0011138916015625}, "domain": "pixel"}, {"position": {"minX": 444.75, "minY": 116.875, "maxX": 456.75, "maxY": 127.375}, "class_id": 3, "box_caption": "open_circuit 0.001", "scores": {"class_score": 0.0010938644409179688}, "domain": "pixel"}, {"position": {"minX": 588.0, "minY": 568.5, "maxX": 620.0, "maxY": 596.5}, "class_id": 5, "box_caption": "spur 0.001", "scores": {"class_score": 0.0010862350463867188}, "domain": "pixel"}, {"position": {"minX": 556.5, "minY": 16.125, "maxX": 585.5, "maxY": 91.4375}, "class_id": 6, "box_caption": "spurious_copper 0.001", "scores": {"class_score": 0.001071929931640625}, "domain": "pixel"}], "class_labels": {"0": "back_ground", "1": "missing_hole", "2": "mouse_bite", "3": "open_circuit", "4": "short", "5": "spur", "6": "spurious_copper"}}